tiara/__init__.py
tiara/constants.py
tiara/main.py
tiara/params.py
tiara/models/__init__.py
tiara/models/nnet-models/__init__.py
tiara/models/nnet-models/first_nnet_kmer_4.pkl
tiara/models/nnet-models/first_nnet_kmer_5.pkl
tiara/models/nnet-models/first_nnet_kmer_6.pkl
tiara/models/nnet-models/second_nnet_kmer_4.pkl
tiara/models/nnet-models/second_nnet_kmer_5.pkl
tiara/models/nnet-models/second_nnet_kmer_6.pkl
tiara/models/nnet-models/second_nnet_kmer_7.pkl
tiara/models/tfidf-models/__init__.py
tiara/models/tfidf-models/k4-first-stage/model.npy
tiara/models/tfidf-models/k4-first-stage/params.txt
tiara/models/tfidf-models/k4-second-stage/model.npy
tiara/models/tfidf-models/k4-second-stage/params.txt
tiara/models/tfidf-models/k5-first-stage/model.npy
tiara/models/tfidf-models/k5-first-stage/params.txt
tiara/models/tfidf-models/k5-second-stage/model.npy
tiara/models/tfidf-models/k5-second-stage/params.txt
tiara/models/tfidf-models/k6-first-stage/model.npy
tiara/models/tfidf-models/k6-first-stage/params.txt
tiara/models/tfidf-models/k6-second-stage/model.npy
tiara/models/tfidf-models/k6-second-stage/params.txt
tiara/models/tfidf-models/k7-second-stage/model.npy
tiara/models/tfidf-models/k7-second-stage/params.txt
tiara/src/__init__.py
tiara/src/bow.py
tiara/src/classification.py
tiara/src/models.py
tiara/src/prediction.py
tiara/src/transformations.py
tiara/src/utilities.py
tiara/test/.DS_Store
tiara/test/__init__.py
tiara/test/test.py
tiara/test/test_data/archaea_fr.fasta.gz
tiara/test/test_data/archaea_out.txt
tiara/test/test_data/bacteria_fr.fasta.gz
tiara/test/test_data/bacteria_out.txt
tiara/test/test_data/eukarya_fr.fasta.gz
tiara/test/test_data/eukarya_out.txt
tiara/test/test_data/log_archaea_out.txt
tiara/test/test_data/log_archea_out.txt
tiara/test/test_data/log_bacteria_out.txt
tiara/test/test_data/log_eukarya_out.txt
tiara/test/test_data/log_mitochondria_out.txt
tiara/test/test_data/log_plast_out.txt
tiara/test/test_data/mitochondria_fr.fasta.gz
tiara-1.0.3.dist-info/LICENSE
tiara-1.0.3.dist-info/METADATA
tiara-1.0.3.dist-info/WHEEL
tiara-1.0.3.dist-info/entry_points.txt
tiara-1.0.3.dist-info/top_level.txt
tiara-1.0.3.dist-info/RECORD
