Metadata-Version: 2.1
Name: tiara
Version: 1.0.3
Summary: A tool for classifying metagenomic data
Home-page: https://ibe-uw.github.io/tiara/
Author: Michał Karlicki
Author-email: Stanisław Antonowicz <stas.antonowicz@gmail.com>
Project-URL: Homepage, https://ibe-uw.github.io/tiara/
Project-URL: Bug Tracker, https://github.com/ibe-uw/tiara/issues
Keywords: machine-learning,computational-biology
Classifier: Programming Language :: Python :: 3.8
Classifier: License :: OSI Approved :: MIT License
Classifier: Operating System :: OS Independent
Requires-Python: >=3.7,<3.10
License-File: LICENSE
Requires-Dist: biopython (~=1.78)
Requires-Dist: joblib (~=0.17.0)
Requires-Dist: numba (>=0.52.0rc3)
Requires-Dist: numpy (~=1.19.4)
Requires-Dist: skorch (~=0.9.0)
Requires-Dist: torch (~=1.7.0)
Requires-Dist: tqdm (~=4.54.0)
